godml/__init__.py
godml/build_doc_index.py
godml/godml_cli.py
godml/notebook_api.py
godml/test_doc_rag.py
godml/advisor_service/__init__.py
godml/advisor_service/advisor_orchestrator.py
godml/advisor_service/data_quality_judge.py
godml/advisor_service/doc_rag_advisor.py
godml/advisor_service/hyperparam_advisor.py
godml/advisor_service/llm_advisor.py
godml/advisor_service/metric_judge.py
godml/advisor_service/model_selector.py
godml/advisor_service/rag_advisor.py
godml/advisor_service/schemas.py
godml/compliance_service/__init__.py
godml/compliance_service/base_compliance.py
godml/compliance_service/compliance_registry.py
godml/compliance_service/compliance_utils.py
godml/compliance_service/pci_dss.py
godml/compliance_service/pii_detector.py
godml/compliance_service/validation_helpers.py
godml/config_service/__init__.py
godml/config_service/loader.py
godml/config_service/resolver.py
godml/config_service/schema.py
godml/core_service/__init__.py
godml/core_service/engine.py
godml/core_service/executors.py
godml/core_service/parser.py
godml/core_service/pipeline_runner.py
godml/core_service/preprocessor.py
godml/core_service/run_pipeline.py
godml/core_service/validators.py
godml/dataprep_service/cli.py
godml/dataprep_service/recipe_executor.py
godml/dataprep_service/schema.py
godml/dataprep_service/connectors/base.py
godml/dataprep_service/connectors/csv.py
godml/dataprep_service/connectors/parquet.py
godml/dataprep_service/connectors/s3.py
godml/dataprep_service/lineage/openlineage_emitter.py
godml/dataprep_service/transforms/base.py
godml/dataprep_service/transforms/cast_types.py
godml/dataprep_service/transforms/columns.py
godml/dataprep_service/transforms/dedup.py
godml/dataprep_service/transforms/encode.py
godml/dataprep_service/transforms/join.py
godml/dataprep_service/transforms/missing.py
godml/dataprep_service/transforms/quality.py
godml/dataprep_service/transforms/scale.py
godml/dataprep_service/transforms/setup.py
godml/dataprep_service/transforms/text.py
godml-0.4.9.dist-info/licenses/LICENSE
godml-0.4.9.dist-info/licenses/LICENSE_REPORT.md
godml-0.4.9.dist-info/METADATA
godml-0.4.9.dist-info/WHEEL
godml-0.4.9.dist-info/entry_points.txt
godml-0.4.9.dist-info/top_level.txt
godml-0.4.9.dist-info/RECORD
