Metadata-Version: 2.4
Name: godml
Version: 0.4.9
Summary: Governed, Observable & Declarative Machine Learning Framework
Author-email: Arturo Gutierrez Rubio Rojas <agtzrubio@dagmalia.com>
License: Apache-2.0
Keywords: mlops,machine learning,framework,governance,observability,mlflow
Classifier: Development Status :: 4 - Beta
Classifier: Intended Audience :: Developers
Classifier: Programming Language :: Python :: 3.10
Classifier: Programming Language :: Python :: 3.11
Classifier: Topic :: Scientific/Engineering :: Artificial Intelligence
Classifier: Topic :: Software Development :: Libraries :: Application Frameworks
Requires-Python: <=3.13,>=3.8
License-File: LICENSE
License-File: LICENSE_REPORT.md
Requires-Dist: typer==0.12.3
Requires-Dist: click==8.1.3
Requires-Dist: protobuf==4.25.8
Requires-Dist: tensorflow==2.17.1
Requires-Dist: urllib3<3,>=2.5.0
Requires-Dist: pandas==2.3.0
Requires-Dist: numpy<2.0,>=1.24.0
Requires-Dist: scikit-learn==1.5.0
Requires-Dist: xgboost==3.0.2
Requires-Dist: lightgbm==4.6.0
Requires-Dist: mlflow==3.1.1
Requires-Dist: pydantic==2.11.7
Requires-Dist: pyyaml==6.0.2
Requires-Dist: rich==14.0.0
Requires-Dist: boto3>=1.40.0
Requires-Dist: sagemaker==2.237.3
Requires-Dist: gpt4all==2.8.2
Requires-Dist: keras==3.11.3
Provides-Extra: api
Requires-Dist: fastapi; extra == "api"
Requires-Dist: uvicorn[standard]; extra == "api"
Requires-Dist: joblib; extra == "api"
Dynamic: license-file
